lz4ext.pyd
lz4ext-0.7.4.dist-info/DESCRIPTION.rst
lz4ext-0.7.4.dist-info/METADATA
lz4ext-0.7.4.dist-info/metadata.json
lz4ext-0.7.4.dist-info/RECORD
lz4ext-0.7.4.dist-info/top_level.txt
lz4ext-0.7.4.dist-info/WHEEL
