Metadata-Version: 2.0
Name: lz4ext
Version: 0.7.4
Summary: LZ4 Bindings for Python
Home-page: https://github.com/sigman78/python-lz4
Author: Steeve Morin, Anton Stuk
Author-email: steeve.morin@gmail.com, sigman@ioupg.com
License: UNKNOWN
Platform: UNKNOWN
Classifier: Development Status :: 5 - Production/Stable
Classifier: License :: OSI Approved :: BSD License
Classifier: Intended Audience :: Developers
Classifier: Programming Language :: C
Classifier: Programming Language :: Python
Classifier: Programming Language :: Python :: 2.6
Classifier: Programming Language :: Python :: 2.7
Classifier: Programming Language :: Python :: 3.3
